attensors/__init__.py
attensors/tensors.py
attensors-0.1.0.dist-info/METADATA
attensors-0.1.0.dist-info/WHEEL
attensors-0.1.0.dist-info/licenses/LICENSE
attensors-0.1.0.dist-info/RECORD
