Metadata-Version: 2.1
Name: attensors
Version: 0.1.0
Summary: Using attrs and numpy to define clear data structures with multiple tensors
Project-URL: Documentation, https://github.com/Optimal-Play/attensors#readme
Project-URL: Issues, https://github.com/Optimal-Play/attensors/issues
Project-URL: Source, https://github.com/Optimal-Play/attensors
Author-email: Sergiu Turlea <sergiu.turlea@gmail.com>
License-Expression: MIT
License-File: LICENSE
Keywords: attribute,tensor
Classifier: Development Status :: 4 - Beta
Classifier: Intended Audience :: Developers
Classifier: Intended Audience :: Science/Research
Classifier: License :: OSI Approved :: MIT License
Classifier: Programming Language :: Python :: 3.9
Classifier: Programming Language :: Python :: 3.10
Classifier: Programming Language :: Python :: 3.11
Classifier: Programming Language :: Python :: Implementation :: CPython
Classifier: Programming Language :: Python :: Implementation :: PyPy
Classifier: Topic :: Scientific/Engineering :: Artificial Intelligence
Classifier: Topic :: Software Development
Classifier: Typing :: Typed
Requires-Python: >=3.9
Requires-Dist: attrs>=21.3.0
Requires-Dist: numpy>=1.20.1
